qcg/pilotjob/executor_api/__init__.py
qcg/pilotjob/executor_api/_version.py
qcg/pilotjob/executor_api/qcgpj_executor.py
qcg/pilotjob/executor_api/qcgpj_future.py
qcg/pilotjob/executor_api/templates/__init__.py
qcg/pilotjob/executor_api/templates/basic_template.py
qcg/pilotjob/executor_api/templates/qcgpj_template.py
qcg_pilotjob_executor_api-0.14.2.dist-info/METADATA
qcg_pilotjob_executor_api-0.14.2.dist-info/WHEEL
qcg_pilotjob_executor_api-0.14.2.dist-info/top_level.txt
qcg_pilotjob_executor_api-0.14.2.dist-info/RECORD
