Metadata-Version: 2.4
Name: qcg-pilotjob-executor-api
Version: 0.14.2
Summary: The executor-like api for QCG-PilotJob
Home-page: http://github.com/vecma-project/QCG-PilotJob
Author: Bartosz Bosak
Author-email: bbosak@man.poznan.pl
Dynamic: author
Dynamic: author-email
Dynamic: description
Dynamic: description-content-type
Dynamic: home-page
Dynamic: summary
